ldjango/__init__.py
ldjango/cli.py
ldjango/landing.py
ldjango/main.py
ldjango/views.py
ldjango/templates/landing_page.html
ldjango-8.5.dist-info/METADATA
ldjango-8.5.dist-info/WHEEL
ldjango-8.5.dist-info/entry_points.txt
ldjango-8.5.dist-info/top_level.txt
ldjango-8.5.dist-info/RECORD
