Metadata-Version: 2.1
Name: ldjango
Version: 8.5
Summary: CLI tool for creating Django projects with a predefined structure.
Author: Liaranda
Author-email: hafiztamvan15@gmail.com
License: MIT
Requires-Dist: Click>=8.1.7
Requires-Dist: Django>=5.1.1
Requires-Dist: whitenoise>=6.7.0
Requires-Dist: tqdm>=4.66.5
Requires-Dist: colorama>=0.4.6
Requires-Dist: prompt-toolkit>=3.0.48
Requires-Dist: django-environ>=0.11.2
